{"Name": "SuperDeluxe", "Runtime": 176, "Gener": ["Action", "Crime", "Drama"], "Bio": "An unfaithful newly-wed wife, an estranged father, a priest and an angry son suddenly find themselves in the most unexpected predicaments, each poised to experience their destiny, all on one fateful day.", "Director": ["Thiagarajan Kumararaja"], "Country": "India", "Language": ["Tamil"], "Date": "29 March 2019", "Poster_link": "https://www.imdb.com/title/tt7019942/mediaviewer/rm1159491328", "Cast": [{"actor_id": "nm4043111", "actor_name": "Vijay Sethupathi"}, {"actor_id": "nm1335704", "actor_name": "Fahadh Faasil"}, {"actor_id": "nm3606487", "actor_name": "Samantha Ruth Prabhu"}, {"actor_id": "nm0471447", "actor_name": "Ramya Krishnan"}, {"actor_id": "nm4199426", "actor_name": "Myshkin"}, {"actor_id": "nm5408984", "actor_name": "Bagavathi Perumal"}, {"actor_id": "nm5408141", "actor_name": "Gayathrie"}, {"actor_id": "nm1056884", "actor_name": "Ashwanth Ashokkumar"}, {"actor_id": "nm1080194", "actor_name": "Jayanth"}, {"actor_id": "nm1058476", "actor_name": "Mirnalini Ravi"}, {"actor_id": "nm1080194", "actor_name": "Noble"}, {"actor_id": "nm1056894", "actor_name": "Vijay Ram"}, {"actor_id": "nm1056894", "actor_name": "Abdul Jabbar"}, {"actor_id": "nm1080194", "actor_name": "Naveen"}, {"actor_id": "nm1056894", "actor_name": "Manushyaputhiran"}, {"actor_id": "nm1080194", "actor_name": "Rengarajan Rajagopalan"}, {"actor_id": "nm1080195", "actor_name": "Kavin Jay Balaji"}, {"actor_id": "nm9821117", "actor_name": "Vivek Raju"}]}