[{"actor_id": "nm1633541", "actor_name": "Ranbir Kapoor"}, {"actor_id": "nm1231899", "actor_name": "Priyanka Chopra"}, {"actor_id": "nm2299825", "actor_name": "Ileana D'Cruz"}, {"actor_id": "nm0795661", "actor_name": "Saurabh Shukla"}, {"actor_id": "nm0304345", "actor_name": "Rupa Ganguly"}, {"actor_id": "nm0896573", "actor_name": "Ashish Vidyarthi"}, {"actor_id": "nm5269876", "actor_name": "Bholaraj Sapkota"}, {"actor_id": "nm1702868", "actor_name": "Jishu Sengupta"}, {"actor_id": "nm0052329", "actor_name": "Haradhan Bannerjee"}, {"actor_id": "nm0452021", "actor_name": "Akash Khurana"}, {"actor_id": "nm0050187", "actor_name": "Arun Bali"}, {"actor_id": "nm1277705", "actor_name": "Uday Tikekar"}, {"actor_id": "nm3472437", "actor_name": "Preiti Mamgain"}, {"actor_id": "nm3817076", "actor_name": "Sumona Chakravarti"}, {"actor_id": "nm2585314", "actor_name": "Sujata Sehgal"}, {"actor_id": "nm1199163", "actor_name": "Kenneth Desai"}, {"actor_id": "nm3124482", "actor_name": "Neeraj Khetrapal"}, {"actor_id": "nm2287214", "actor_name": "Rajeev Mishra"}, {"actor_id": "nm6740068", "actor_name": "Nirmala D. Thappa"}, {"actor_id": "nm6740069", "actor_name": "Apurva Pranjape"}, {"actor_id": "nm6740070", "actor_name": "Rahul Malhothra"}, {"actor_id": "nm6740071", "actor_name": "Bhagyashree Dembla"}, {"actor_id": "nm6740072", "actor_name": "Subhankar Ghosh"}, {"actor_id": "nm2414088", "actor_name": "Purva Parag"}, {"actor_id": "nm4820659", "actor_name": "Archana Dani"}, {"actor_id": "nm5269881", "actor_name": "Rahul Garg"}, {"actor_id": "nm5311552", "actor_name": "Nigam Thakur"}]