[{"actor_id": "nm0004570", "actor_name": "Sunil Dutt"}, {"actor_id": "nm0052570", "actor_name": "Saira Banu"}, {"actor_id": "nm0576454", "actor_name": "Mehmood"}, {"actor_id": "nm0474822", "actor_name": "Kishore Kumar"}, {"actor_id": "nm0695170", "actor_name": "Om Prakash"}, {"actor_id": "nm0013023", "actor_name": "Agha"}, {"actor_id": "nm0611617", "actor_name": "Mukri"}, {"actor_id": "nm0839129", "actor_name": "Sunder"}, {"actor_id": "nm0304303", "actor_name": "Ganga"}, {"actor_id": "nm0666951", "actor_name": "Praveen Paul"}, {"actor_id": "nm0611537", "actor_name": "Keshto Mukherjee"}, {"actor_id": "nm0457261", "actor_name": "Raj Kishore"}, {"actor_id": "nm0241291", "actor_name": "Dulari"}, {"actor_id": "nm0711830", "actor_name": "Ratna"}, {"actor_id": "nm1425570", "actor_name": "Moolchand"}, {"actor_id": "nm0417714", "actor_name": "Jankidas"}, {"actor_id": "nm0864609", "actor_name": "Niranjan Tiwari"}]