[{"actor_id": "nm2486247", "actor_name": "Manoj Kumar Manchu"}, {"actor_id": "nm1084853", "actor_name": "Allu Arjun"}, {"actor_id": "nm2011932", "actor_name": "Anushka Shetty"}, {"actor_id": "nm0048075", "actor_name": "Manoj Bajpayee"}, {"actor_id": "nm3945388", "actor_name": "Nagayya"}, {"actor_id": "nm3945751", "actor_name": "Deeksha Seth"}, {"actor_id": "nm3262096", "actor_name": "Lekha Washington"}, {"actor_id": "nm0103977", "actor_name": "Brahmanandam"}, {"actor_id": "nm3884155", "actor_name": "Siya"}, {"actor_id": "nm1152338", "actor_name": "Satyam Rajesh"}, {"actor_id": "nm3046678", "actor_name": "Ravi Prakash"}, {"actor_id": "nm0692586", "actor_name": "Krishna Murali Posani"}, {"actor_id": "nm2179000", "actor_name": "Pruthvi"}, {"actor_id": "nm1298052", "actor_name": "Raghu Babu"}, {"actor_id": "nm4442569", "actor_name": "Joy Badlani"}, {"actor_id": "nm0157262", "actor_name": "Kallu Chidambaram"}, {"actor_id": "nm4827987", "actor_name": "Sammeta Gandhi"}, {"actor_id": "nm2145958", "actor_name": "Vajja Venkata Giridhar"}, {"actor_id": "nm3758453", "actor_name": "Radha Krishna Jagarlamudi"}, {"actor_id": "nm4031719", "actor_name": "Nagineedu"}, {"actor_id": "nm0764853", "actor_name": "Saranya Ponvannan"}, {"actor_id": "nm6004604", "actor_name": "Rakesh Varre"}]